MANIFEST.in
README.rst
setup.py
aliyun_python_sdk_iqa.egg-info/PKG-INFO
aliyun_python_sdk_iqa.egg-info/SOURCES.txt
aliyun_python_sdk_iqa.egg-info/dependency_links.txt
aliyun_python_sdk_iqa.egg-info/requires.txt
aliyun_python_sdk_iqa.egg-info/top_level.txt
aliyunsdkiqa/__init__.py
aliyunsdkiqa/request/__init__.py
aliyunsdkiqa/request/v20190813/CreateProjectRequest.py
aliyunsdkiqa/request/v20190813/DeleteProjectRequest.py
aliyunsdkiqa/request/v20190813/DeployServiceRequest.py
aliyunsdkiqa/request/v20190813/DescribeProjectRequest.py
aliyunsdkiqa/request/v20190813/GetPredictResultRequest.py
aliyunsdkiqa/request/v20190813/ListProjectsRequest.py
aliyunsdkiqa/request/v20190813/ModifiyProjectRequest.py
aliyunsdkiqa/request/v20190813/UploadDictionaryRequest.py
aliyunsdkiqa/request/v20190813/UploadDocumentRequest.py
aliyunsdkiqa/request/v20190813/__init__.py